ipyplot/__init__.py
ipyplot/_html_helpers.py
ipyplot/_img_helpers.py
ipyplot/_plotting.py
ipyplot/_utils.py
ipyplot-1.1.1.dist-info/LICENSE
ipyplot-1.1.1.dist-info/METADATA
ipyplot-1.1.1.dist-info/WHEEL
ipyplot-1.1.1.dist-info/top_level.txt
ipyplot-1.1.1.dist-info/RECORD
