Metadata-Version: 2.1
Name: ipyplot
Version: 1.1.1
Summary: Simple package that leverages IPython and HTML for more efficient, reach and interactive plotting of images in Jupyter Notebooks
Home-page: http://github.com/karolzak/ipyplot
Author: Karol Zak
Author-email: karol.zak@hotmail.com
License: MIT
Platform: UNKNOWN
Classifier: Development Status :: 5 - Production/Stable
Classifier: Intended Audience :: Developers
Classifier: Intended Audience :: Education
Classifier: Intended Audience :: Science/Research
Classifier: License :: OSI Approved :: MIT License
Classifier: Programming Language :: Python :: 3.5
Classifier: Programming Language :: Python :: 3.6
Classifier: Programming Language :: Python :: 3.7
Classifier: Programming Language :: Python :: 3.8
Classifier: Topic :: Software Development :: Libraries
Classifier: Topic :: Software Development :: Libraries :: Python Modules
License-File: LICENSE
Requires-Dist: IPython
Requires-Dist: numpy
Requires-Dist: pillow
Requires-Dist: shortuuid
